best_sort/__init__.py
best_sort/_version.py
best_sort/compare_engine/__init__.py
best_sort/compare_engine/compare.py
best_sort/sort_algos/__init__.py
best_sort/sort_algos/bubble_sort.py
best_sort/sort_algos/insertion_sort.py
best_sort/sort_algos/selection_sort.py
best_sort/visual_aids/__init__.py
best_sort/visual_aids/graph_comparison.py
best_sort-0.0.11.dist-info/WHEEL
best_sort-0.0.11.dist-info/METADATA
best_sort-0.0.11.dist-info/RECORD
